class_doc.py
class_doc-0.2.5.dist-info/WHEEL
class_doc-0.2.5.dist-info/METADATA
class_doc-0.2.5.dist-info/RECORD
