Metadata-Version: 2.1
Name: class-doc
Version: 0.2.5
Summary: Extract attributes docstrings defined in various ways
Home-page: https://github.com/danields761/class-doc
License: MIT
Author: Daniel Daniels
Author-email: danields761@gmail.com
Requires-Python: >=3.6,<4.0
Classifier: Development Status :: 3 - Alpha
Classifier: Intended Audience :: Developers
Classifier: License :: OSI Approved :: MIT License
Classifier: Operating System :: OS Independent
Classifier: Programming Language :: Python
Classifier: Programming Language :: Python :: 3
Classifier: Programming Language :: Python :: 3 :: Only
Classifier: Programming Language :: Python :: 3.6
Classifier: Programming Language :: Python :: 3.7
Classifier: Programming Language :: Python :: 3.8
Classifier: Topic :: Internet
Classifier: Topic :: Software Development :: Libraries :: Python Modules
Requires-Dist: more-itertools (>=7.2,<8.0)
Project-URL: Repository, https://github.com/danields761/class-doc
